robotransform/__init__.py
robotransform/__main__.py
robotransform/aadl.py
robotransform/concepts.py
robotransform/convert.py
robotransform/filters.py
robotransform/main.py
robotransform/processors.py
robotransform/robochart.tx
robotransform/templates/aadl.jinja
robotransform/templates/messages.aadl.jinja
robotransform-0.1.0.dist-info/WHEEL
robotransform-0.1.0.dist-info/entry_points.txt
robotransform-0.1.0.dist-info/METADATA
robotransform-0.1.0.dist-info/RECORD
