Metadata-Version: 2.3
Name: robotransform
Version: 0.1.0
Summary: Perform model transformations for the RoboSapiens project.
Keywords: transformation
Author: Arkadiusz Michał Ryś
Author-email: Arkadiusz Michał Ryś <Arkadiusz.Michal.Rys@gmail.com>
License:                     GNU GENERAL PUBLIC LICENSE
Classifier: Development Status :: 2 - Pre-Alpha
Classifier: Intended Audience :: Developers
Classifier: Natural Language :: English
Classifier: Programming Language :: Python :: 3
Requires-Dist: arklog>=0.7.0,<1
Requires-Dist: arkfast>=0.1.0,<1
Requires-Dist: textx>=4.2.3,<5
Requires-Dist: jinja2>=3.1.6,<4
Requires-Dist: pyecore>=0.15.2,<1
Requires-Python: >=3.14
Project-URL: source, https://git.rys.one/phd/robosapiens/robotransform
Provides-Extra: gui
